heat_cfntools/__init__.py
heat_cfntools/cfntools/__init__.py
heat_cfntools/cfntools/cfn_helper.py
heat_cfntools/tests/__init__.py
heat_cfntools/tests/test_cfn_helper.py
heat_cfntools/tests/test_cfn_hup.py
heat_cfntools-2.0.0.data/scripts/cfn-create-aws-symlinks
heat_cfntools-2.0.0.data/scripts/cfn-get-metadata
heat_cfntools-2.0.0.data/scripts/cfn-hup
heat_cfntools-2.0.0.data/scripts/cfn-init
heat_cfntools-2.0.0.data/scripts/cfn-push-stats
heat_cfntools-2.0.0.data/scripts/cfn-signal
heat_cfntools-2.0.0.dist-info/AUTHORS
heat_cfntools-2.0.0.dist-info/LICENSE
heat_cfntools-2.0.0.dist-info/METADATA
heat_cfntools-2.0.0.dist-info/WHEEL
heat_cfntools-2.0.0.dist-info/pbr.json
heat_cfntools-2.0.0.dist-info/top_level.txt
heat_cfntools-2.0.0.dist-info/RECORD
