Metadata-Version: 2.1
Name: heat-cfntools
Version: 2.0.0
Summary: Tools required to be installed on Heat provisioned cloud instances
Home-page: https://docs.openstack.org/heat-cfntools/latest/
Author: OpenStack
Author-email: openstack-discuss@lists.openstack.org
License: UNKNOWN
Platform: UNKNOWN
Classifier: Environment :: OpenStack
Classifier: Intended Audience :: Information Technology
Classifier: Intended Audience :: System Administrators
Classifier: License :: OSI Approved :: Apache Software License
Classifier: Operating System :: POSIX :: Linux
Classifier: Programming Language :: Python
Classifier: Programming Language :: Python :: 3
Classifier: Programming Language :: Python :: 3.6
Classifier: Programming Language :: Python :: 3.7
Classifier: Programming Language :: Python :: 3.8
Requires-Python: >=3.6
Requires-Dist: boto (>=2.32.1)
Requires-Dist: pbr (!=2.1.0,>=2.0.0)
Requires-Dist: psutil (>=1.1.1)
Requires-Dist: six (>=1.9.0)
